{
  "$comment": "Bug 1635959 - A ping for debugging the Pioneer v2 pipeline.",
  "$schema": "http://json-schema.org/draft-04/schema#",
  "mozPipelineMetadata": {
    "bq_dataset_family": "pioneer_debug",
    "bq_metadata_format": "structured",
    "bq_table": "debug_v1"
  },
  "properties": {
    "datetime": {
      "description": "An ISO 8601 datetime string.",
      "format": "date-time",
      "type": "string"
    }
  },
  "required": [
    "datetime"
  ],
  "title": "debug",
  "type": "object"
}
